{
  "xVisible4": "0.0",
  "xVisible5": "0.0",
  "xVisible2": "0.0",
  "yVisible5": "0.0",
  "xVisible3": "0.0",
  "yVisible6": "0.0",
  "yVisible3": "0.0",
  "yVisible4": "0.0",
  "xVisible6": "0.0",
  "yVisible1": "1.0",
  "yVisible2": "0.0",
  "zAxisMaxY": "-1",
  "xMultiplier6": "2",
  "xMultiplier5": "0",
  "xMultiplier4": "0",
  "xMultiplier3": "2",
  "xVisible1": "1.0",
  "xMultiplier2": "0",
  "xMultiplier1": "1",
  "yAxisMaxY": "-1",
  "xAxisMaxY": "-1",
  "zMultiplier5": "3",
  "zMultiplier6": "5",
  "zMultiplier3": "2",
  "zMultiplier4": "2",
  "zMultiplier1": "0.03",
  "zMultiplier2": "0",
  "yMultiplier3": "0.1",
  "yMultiplier2": "0",
  "xAxisMinY": "1",
  "yMultiplier5": "0",
  "yMultiplier4": "0",
  "yMultiplier6": "3",
  "yAxisMinY": "1",
  "zVisible3": "0.0",
  "zAxisMinY": "1",
  "zVisible2": "0.0",
  "zVisible1": "1.0",
  "zVisible6": "0.0",
  "yMultiplier1": "0.03",
  "zVisible5": "0.0",
  "zVisible4": "0.0"
}